{
    "[__split__]Colorful Cute!": "[__split__]Colorful Cute!",
    "[__split__]POW！": "[__split__]POW!",
    "[__split__]Upgraded": "[__split__]Upgraded",
    "[__split__]あのときの約束": "[__split__]그때의 약속",
    "[__split__]あふれる思い出": "[__split__]넘쳐나는 추억",
    "[__split__]ありがとうの言葉": "[__split__]감사의 말",
    "[__split__]いっしょけんめい": "[__split__]いっしょけんめい",
    "[__split__]えいえいおー": "[__split__]에이이이오!",
    "[__split__]おっきなおにぎり": "[__split__]오키나 오니기리",
    "[__split__]おアツイ視線": "[__split__]뜨거운 시선",
    "[__split__]お姉ちゃんだもの！": "[__split__]언니잖아!",
    "[__split__]お嬢様の晴れ舞台": "[__split__]아가씨들의晴れ舞台",
    "[__split__]お泊り猛勉強": "[__split__]밤샘 맹공부",
    "[__split__]きみと分け合う夏": "[__split__]너와 함께 나누는 여름",
    "[__split__]ご指導ご鞭撻": "[__split__]ご指導ご鞭撻",
    "[__split__]それぞれの道": "[__split__]각자의 길",
    "[__split__]なに聴いてるの？": "[__split__]뭐 듣고 계세요?",
    "[__split__]はじける水しぶき": "[__split__]터지는 물보라",
    "[__split__]ひと呼吸": "[__split__]한숨",
    "[__split__]ひなたぼっこ": "[__split__]히나타보코",
    "[__split__]ひんやり一休み": "[__split__]시원한 휴식",
    "[__split__]ふれあい": "[__split__]만남",
    "[__split__]みずたまりスキップ": "[__split__]물웅덩이 건너뛰기",
    "[__split__]みんな大好き": "[__split__]모두 사랑해",
    "[__split__]もう少しだけ": "[__split__]조금만 더",
    "[__split__]もう怖くないから": "[__split__]더 이상 무섭지 않으니까요.",
    "[__split__]やる気は満点": "[__split__]의욕은 만점!",
    "[__split__]ゆめみごこち": "[__split__]유메미 고코치",
    "[__split__]ゆるふわおしゃべり": "[__split__]느슨한 수다",
    "[__split__]よそ見はダメ♪": "[__split__]눈치 보지 말아요",
    "[__split__]らしさ": "[__split__] 같음",
    "[__split__]アイドル宣言": "[__split__]아이돌 선언",
    "[__split__]アイドル魂": "[__split__]아이돌 소울",
    "[__split__]アドリブ": "[__split__]애드리브",
    "[__split__]アドレナリン全開": "[__split__]아드레날린 풀가동",
    "[__split__]アピールの基本": "[__split__] 어필의 기본",
    "[__split__]アルバイター": "[__split__]아르바이트생",
    "[__split__]イメトレ": "[__split__]이메토레",
    "[__split__]オトメゴコロ": "[__split__]오토메고코로",
    "[__split__]カエル印の扇風機": "[__split__]개구리 모양의 선풍기",
    "[__split__]キメ顔で自撮り": "[__split__]표정으로 셀카 찍기",
    "[__split__]キラメキ": "[__split__]반짝임",
    "[__split__]コール＆レスポンス": "[__split__]콜 &amp; 리스폰스",
    "[__split__]シュプレヒコール": "[__split__]슈프레히콜",
    "[__split__]スタンドプレー": "[__split__]스탠드 플레이",
    "[__split__]スタートダッシュ": "[__split__]시작 대시",
    "[__split__]ストレッチ談義": "[__split__] 스트레칭 담론",
    "[__split__]スポットライト": "스포트 라이트 [__split__] 스포트라이트",
    "[__split__]スマイル": "스마일 [__split__]스마일",
    "[__split__]ダメダメクッキング": "[__split__]안돼 안돼 요리",
    "[__split__]ティーパーティ": "[__split__]티 파티",
    "[__split__]テレビ出演": "[__split__]TV 출연",
    "[__split__]トキメキ": "[__split__]토키메키",
    "[__split__]トークタイム": "[__split__]토크 타임",
    "[__split__]ノートの端の決意": "[__split__]노트 끝의 결의 노트 끝의 결심",
    "[__split__]ハイタッチ": "[__split__]하이터치",
    "[__split__]ハイテンション": "[__split__]하이텐션",
    "[__split__]ハートの合図": "[__split__] 하트 시그널",
    "[__split__]バスに揺られて": "[__split__]버스에 흔들리며",
    "[__split__]バズワード": "[__split__] 버즈워드",
    "[__split__]バランス感覚": "[__split__]균형감각",
    "[__split__]パステル気分": "[__split__]파스텔 무드",
    "[__split__]ファンサ": "[__split__]팬사",
    "[__split__]ファンシーチャーム": "[__split__]팬시 매력",
    "[__split__]ファーストステップ": "[__split__]첫 번째 단계",
    "[__split__]フレンドリー": "[__split__]친근한",
    "[__split__]ポーズの基本": "[__split__]포즈의 기본",
    "[__split__]ラブリーウインク": "[__split__]러블리 윙크",
    "[__split__]リスタート": "[__split__] 리스타트",
    "[__split__]リズミカル": "[__split__] 리드미컬한",
    "[__split__]リトル・プリンス": "[__split__]리틀 프린스",
    "[__split__]ローン・ウルフ": "[__split__]론 울프",
    "[__split__]ワクワクが止まらない": "[__split__]설레임이 멈추지 않는다!",
    "[__split__]ワンモアステップ": "[__split__]원모어스텝",
    "[__split__]一番は譲らない": "[__split__]제일은 양보할 수 없어",
    "[__split__]今日もおはよう": "[__split__]오늘도 좋은 하루 되세요",
    "[__split__]仕切り直し": "[__split__]재분할",
    "[__split__]元気いっぱい": "[__split__]활기차다",
    "[__split__]元気な挨拶": "[__split__]힘내세요!",
    "[__split__]光のステージ": "[__split__]빛의 스테이지",
    "[__split__]入道雲と、きみ": "[__split__]입도운과, 키미",
    "[__split__]全力サポート": "[__split__] 전폭적인 지원",
    "[__split__]内気系少女": "[__split__]수줍음 많은 소녀",
    "[__split__]前途洋々": "[__split__]前途洋々",
    "[__split__]励まし": "[__split__]격려",
    "[__split__]勇気の一歩": "[__split__]용기의 한 걸음",
    "[__split__]勢い任せ": "[__split__]기세에 눌려서",
    "[__split__]包容力": "[__split__]포용력",
    "[__split__]可愛い仕草": "[__split__]귀여운 동작",
    "[__split__]叶えたい夢": "[__split__]이루고 싶은 꿈",
    "[__split__]喧嘩するほど仲がいい": "[__split__]싸우면 싸울수록 사이가 좋다",
    "[__split__]国民的アイドル": "[__split__]국민 아이돌",
    "[__split__]大声援": "[__split__]큰 응원",
    "[__split__]天真爛漫": "[__split__]天真爛漫",
    "[__split__]始まりの合図": "[__split__]시작의 신호",
    "[__split__]存在感": "[__split__]존재감",
    "[__split__]寄り添う気持ち": "[__split__] 껴안는 마음",
    "[__split__]届いて！": "[__split__]도착했습니다!",
    "[__split__]幸せな時間": "[__split__]행복한 시간",
    "[__split__]幸せのおまじない": "[__split__]행복의 주문",
    "[__split__]心のアルバム": "[__split__]마음의 앨범",
    "[__split__]思い出し笑い": "[__split__]추억의 웃음",
    "[__split__]情熱ターン": "열정 턴 [__split__]열정 턴",
    "[__split__]意地": "[__split__]의지",
    "[__split__]意地っ張り": "[__split__]고집불통",
    "[__split__]意識の基本": "[__split__]의식의 기본",
    "[__split__]愛嬌": "[__split__]애교",
    "[__split__]成功への道筋": "성공으로 가는 길 [__split__]성공으로 가는 길",
    "[__split__]成就": "[__split__]성취",
    "[__split__]手拍子": "[__split__]손뼉을 칩니다.",
    "[__split__]手書きのメッセージ": "[__split__]손글씨 메시지",
    "[__split__]打倒お姉ちゃん": "[__split__]타도 누나",
    "[__split__]挑戦": "[__split__] 챌린지",
    "[__split__]振る舞いの基本": "[__split__] 행동의 기본",
    "[__split__]新生徒会爆誕！": "[__split__]신학생회 폭탄 탄생!",
    "[__split__]新進気鋭": "[__split__]신예",
    "[__split__]星屑センセーション": "[__split__]별똥별 센세이션",
    "[__split__]昼下がりのそよ風": "[__split__]한낮의 산들바람",
    "[__split__]最後の夏の思い出": "[__split__]마지막 여름의 추억",
    "[__split__]未完の大器": "[미완성된 대기",
    "[__split__]本気の趣味": "[__split__]진지한 취미",
    "[__split__]本番前夜": "[__split__]방송 전날 밤",
    "[__split__]楽観的": "[__split__]낙관적",
    "[__split__]止められない想い": "[__split__]멈출 수 없는 마음",
    "[__split__]気分転換": "[기분 전환",
    "[__split__]気合十分！": "[__split__]기합이 충분합니다!",
    "[__split__]決めポーズ": "[__split__]결정 포즈",
    "[__split__]深呼吸": "[__split__]심호흡",
    "[__split__]準備運動": "[__split__]준비운동",
    "[__split__]演出計画": "[__split__] 연출 계획",
    "[__split__]盛装の華形": "[__split__]성장의 꽃 모양",
    "[__split__]目線の基本": "[__split__]시선의 기본",
    "[__split__]眠気": "[__split__]졸음",
    "[__split__]眼力": "[__split__]눈빛",
    "[__split__]祝福": "[__split__]축복",
    "[__split__]私がスター": "[__split__]내가 스타",
    "[__split__]立ち位置チェック": "[__split__]서있는 위치 확인",
    "[__split__]純白の妖精": "[__split__]순백의 요정",
    "[__split__]絡まる想い": "[__split__]얽히고설킨 마음",
    "[__split__]絶対に負けない": "절대 지지 않을 [__split__]절대 지지 않는다",
    "[__split__]至高のエンタメ": "[__split__]최고의 엔터테인먼트",
    "[__split__]花萌ゆ季節": "[__split__]花萌ゆ季節",
    "[__split__]苦しいのが好き": "[__split__]괴로운 것을 좋아한다.",
    "[__split__]薄れゆく壁": "[__split__]희미해져 가는 벽",
    "[__split__]虹色ドリーマー": "[__split__]무지개빛 몽상가",
    "[__split__]表情の基本": "[__split__] 표정의 기본",
    "[__split__]表現の基本": "[__split__] 표현의 기초",
    "[__split__]覚醒": "[__split__]각성",
    "[__split__]試行錯誤": "[__split__] 시행착오",
    "[__split__]超高学歴アイドル": "[__split__]초고학력 아이돌",
    "[__split__]距離感": "[__split__]거리감",
    "[__split__]軽い足取り": "[__split__]가벼운 발걸음",
    "[__split__]輝くキミへ": "[__split__]빛나는 너에게",
    "[__split__]開花": "[__split__]개화",
    "[__split__]陽だまりの生徒会室": "[__split__]양지바른 학생회실",
    "[__split__]静かな意志": "[__split__]조용한 의지",
    "[__split__]願いの力": "[__split__]소원의 힘",
    "[__split__]飛躍": "[__split__]도약",
    "[__split__]魅惑のパフォーマンス": "[__split__]매혹적인 퍼포먼스",
    "[__split__]魅惑の視線": "[__split__]매혹적인 시선",
    "[__split__]鳴り止まない拍手": "[__split__]멈추지 않는 박수소리"
}